[{"s": "bezopasnaya-pokupka-sdek-kak-rabotaet", "t": "Как безопасно купить через СДЭК: пошаговая инструкция 2026", "i": "🛡️", "c": "bezopasnost"}, {"s": "bezopasnaya-sdelka-sdek-chto-eto-takoe-otzyvy", "t": "Безопасная сделка СДЭК: что это, как работает, реальные отзывы 2026", "i": "🛡️", "c": "bezopasnost"}, {"s": "bezopasnaya-sdelka-ot-sdeka-chto-eto", "t": "Безопасная сделка СДЭК: что это и как работает", "i": "📁", "c": null}, {"s": "besplatnoe-khranenie-v-sdek-skolko-dlitsya", "t": "Бесплатное хранение в СДЭК: сколько дней длится и тарифы", "i": "🤲", "c": "poluchenie"}, {"s": "bezopasnaya-sdelka-sdek-avito-kak-rabotaet", "t": "Безопасная сделка СДЭК и Авито: как работает и комиссия", "i": "🛡️", "c": "bezopasnost"}]