[{"s": "kakie-dannye-nuzhny-dlya-oformleniya-posylki-v-sdek", "t": "Какие данные нужны для оформления посылки в СДЭК: полный список 2026", "i": "🚚", "c": "otpravka-gruzov"}, {"s": "kakie-dannye-nuzhny-dlya-otpravki-sdekom", "t": "Какие данные нужны для отправки посылки через СДЭК в 2026 году", "i": "🚚", "c": "otpravka-gruzov"}, {"s": "kakie-dannye-nuzhny-chtob-otpravit-posylku-sdek", "t": "Какие данные нужны для отправки посылки через СДЭК в 2026 году", "i": "🚚", "c": "otpravka-gruzov"}, {"s": "kakie-platnye-uvedomleniya-kompaniya-sdek-predostavlyaet-klientam", "t": "Платные уведомления СДЭК: виды, стоимость и как подключить в 2026", "i": "🔍", "c": "otslezhivanie"}, {"s": "kakie-tipy-avtomobilnykh-akkumulyatornykh-batarej-zapreshcheny-k-perevozke-v-sdek", "t": "Запрещённые аккумуляторы в СДЭК: полный список 2026 года", "i": "🧊", "c": "spetsgruzy"}, {"s": "kakoj-srok-dostavki-sdek", "t": "Сроки доставки СДЭК в 2026: точные данные по регионам и типам грузов", "i": "🚚", "c": "otpravka-gruzov"}, {"s": "kakaya-komissiya-za-nalozhennyj-platezh-sdek", "t": "Комиссия за наложенный платеж в СДЭК 2026: тарифы и нюансы", "i": "💳", "c": "oplata-i-tarify"}, {"s": "kakie-dannye-nado-dlya-otpravki-posylki-sdek", "t": "Какие данные нужны для отправки посылки СДЭК в 2026 году", "i": "🚚", "c": "otpravka-gruzov"}, {"s": "kakie-dannye-nuzhny-dlya-otpravleniya-sdek", "t": "Какие данные нужны для отправки посылки через СДЭК в 2026 году", "i": "🚚", "c": "otpravka-gruzov"}, {"s": "kakaya-podklyuchenie-sdek", "t": "Какое подключение к СДЭК выбрать: сравнение способов 2026", "i": "🤝", "c": "biznes-i-dogovory"}, {"s": "kakie-dokumenty-nuzhno-chtoby-otpravit-posylku-sdek", "t": "Какие документы нужны для отправки посылки СДЭК в 2026 году", "i": "🚚", "c": "otpravka-gruzov"}, {"s": "kakie-etapy-dostavki-v-sdek", "t": "Этапы доставки в СДЭК: от приема до выдачи посылки в 2026 году", "i": "🔍", "c": "otslezhivanie"}, {"s": "kakie-posylki-mozhno-otpravit-sdekom", "t": "Что можно отправить через СДЭК: полный список разрешенных посылок 2026", "i": "🚚", "c": "otpravka-gruzov"}, {"s": "kakie-dannye-poluchatelya-nuzhny-dlya-otpravki-posylki-sdekom", "t": "Какие данные получателя нужны для отправки посылки СДЭК в 2026 году", "i": "🚚", "c": "otpravka-gruzov"}, {"s": "kakoj-dokhod-prinosit-sdeka", "t": "Сколько зарабатывает СДЭК: доходы, прибыль и финансовые показатели 2026", "i": "💳", "c": "oplata-i-tarify"}, {"s": "kakaya-dobavlenie-sdek", "t": "Какая добавка СДЭК нужна для отправки груза? Полный разбор 2026", "i": "💳", "c": "oplata-i-tarify"}, {"s": "kakie-dannye-nuzhny-dlya-otpravki-posylki-sdek-fizicheskomu-litsu", "t": "Какие данные нужны для отправки посылки СДЭК физическому лицу в 2026 году", "i": "🚚", "c": "otpravka-gruzov"}, {"s": "kakie-dannye-nuzhny-dlya-otpravki-sdekom-v-drugoj-gorod", "t": "Какие данные нужны для отправки посылки СДЭК в другой город: полный список 2026", "i": "🚚", "c": "otpravka-gruzov"}, {"s": "kakie-dokumenty-nuzhny-chtoby-zabrat-posylku-v-sdek", "t": "Какие документы нужны для получения посылки в СДЭК 2026: полный список", "i": "🤲", "c": "poluchenie"}, {"s": "kakie-dokumenty-nuzhny-dlya-sdek-dlya-otpravki", "t": "Какие документы нужны для СДЭК при отправке посылки в 2026 году", "i": "🚚", "c": "otpravka-gruzov"}, {"s": "kakim-transportom-dostavlyayutsya-posylki-sdek", "t": "Каким транспортом СДЭК доставляет посылки в 2026 году: виды и особенности", "i": "🚚", "c": "otpravka-gruzov"}, {"s": "kakim-transportom-sdek", "t": "Какой транспорт использует СДЭК для доставки посылок в 2026 году", "i": "🚚", "c": "otpravka-gruzov"}, {"s": "kakaya-transportnaya-kompaniya-deshevle-sdek-ili-energiya", "t": "СДЭК или Энергия: где дешевле отправить груз в 2026 году?", "i": "💳", "c": "oplata-i-tarify"}, {"s": "kakaya-transportnaya-kompaniya-deshevle-sdek-ili-pek", "t": "СДЭК или ПЭК: где дешевле отправить груз в 2026 году? Сравнение тарифов", "i": "💳", "c": "oplata-i-tarify"}, {"s": "kakie-dannye-nuzhny-dlya-otpravki-sdek-otpravitelyu", "t": "Какие данные нужны для отправки СДЭК: полный список 2026", "i": "🚚", "c": "otpravka-gruzov"}, {"s": "kakie-nuzhny-dannye-dlya-otpravki-posylki-po-sdeku", "t": "Какие данные нужны для отправки посылки через СДЭК в 2026 году", "i": "🚚", "c": "otpravka-gruzov"}, {"s": "kakaya-otslezhivat-posylku-sdek", "t": "Как отследить посылку СДЭК: 7 способов + инструкции 2026", "i": "🔍", "c": "otslezhivanie"}, {"s": "kakie-nuzhny-dokumenty-chtoby-otpravit-posylku-sdekom", "t": "Какие документы нужны для отправки посылки СДЭК в 2026 году", "i": "🚚", "c": "otpravka-gruzov"}, {"s": "kakie-dannye-nuzhny-dlya-otpravki-sdek-ot-otpravitelya", "t": "Какие данные нужны для отправки СДЭК от отправителя в 2026 году", "i": "🚚", "c": "otpravka-gruzov"}, {"s": "kakie-dannye-nuzhny-dlya-otpravleniya-posylki-sdek", "t": "Какие данные нужны для отправки посылки СДЭК в 2026 году", "i": "🚚", "c": "otpravka-gruzov"}, {"s": "kakoj-maksimalnyj-gruz-mozhno-otpravit-sdek", "t": "Максимальный вес груза в СДЭК: тарифы и ограничения 2026", "i": "🚚", "c": "otpravka-gruzov"}, {"s": "kakie-dannye-nuzhny-dlya-otpravki-posylki-sdek-v-drugoj-gorod", "t": "Какие данные нужны для отправки посылки СДЭК в другой город 2026", "i": "🚚", "c": "otpravka-gruzov"}, {"s": "kakie-dannye-poluchatelya-nuzhny-dlya-otpravki-sdek-do-punkta-vydachi", "t": "Какие данные получателя нужны для отправки СДЭК до пункта выдачи (ПВЗ)", "i": "🚚", "c": "otpravka-gruzov"}, {"s": "kakie-gruzy-otnosyatsya-k-spetsialnym-gruzam-sdek", "t": "Спецгрузы СДЭК 2026: полный список и правила перевозки", "i": "🧊", "c": "spetsgruzy"}, {"s": "kakie-gruzy-zapreshcheny-k-perevozke-sdek", "t": "Запрещённые грузы СДЭК 2026: полный список и штрафы", "i": "🧊", "c": "spetsgruzy"}, {"s": "kakim-transportom-sdek-dostavlyaet-posylki-v-regiony", "t": "Как СДЭК доставляет посылки в регионы: транспорт, сроки, особенности", "i": "🚚", "c": "otpravka-gruzov"}, {"s": "kakoj-srok-khraneniya-v-sdek", "t": "Срок хранения посылок в СДЭК: правила 2026 года и штрафы за просрочку", "i": "🤲", "c": "poluchenie"}, {"s": "kakie-dannye-neobkhodimy-dlya-otpravki-sdekom", "t": "Какие данные нужны для отправки посылки через СДЭК в 2026 году", "i": "🚚", "c": "otpravka-gruzov"}, {"s": "kakie-gruzy-dostavlyaet-sdek", "t": "Какие грузы доставляет СДЭК: полный перечень 2026 года", "i": "🧊", "c": "spetsgruzy"}, {"s": "kakie-pasportnye-dannye-nuzhny-dlya-transportnoj-kompanii-sdek", "t": "Какие паспортные данные нужны для СДЭК в 2026: полный список", "i": "🤝", "c": "biznes-i-dogovory"}, {"s": "kakoj-srok-khraneniya-posylki-v-sdeke", "t": "Срок хранения посылки в СДЭК 2026: сколько дней и что делать если просрочка", "i": "🤲", "c": "poluchenie"}, {"s": "kakaya-tk-deshevle-sdek-ili-delovye-linii", "t": "СДЭК или Деловая линия: где дешевле отправить груз в 2026 году?", "i": "💳", "c": "oplata-i-tarify"}, {"s": "kakie-dokumenty-nuzhny-dlya-oformleniya-sdek-posylki", "t": "Документы для оформления СДЭК посылки в 2026 году: полный список", "i": "🚚", "c": "otpravka-gruzov"}, {"s": "kakim-sposobom-klient-mozhet-izmenit-summu-nalozhennogo-platezha-v-nakladnoj-sdek", "t": "Как изменить сумму наложенного платежа в накладной СДЭК: 5 способов", "i": "💳", "c": "oplata-i-tarify"}, {"s": "kakoj-dokhod-prinosit-sdek", "t": "Сколько зарабатывает СДЭК: доходы, прибыль и финансовые показатели 2026", "i": "🚚", "c": "otpravka-gruzov"}, {"s": "kakoj-marketplejs-dostavlyaet-sdekom", "t": "Какой маркетплейс доставляет СДЭК: полный список 2026", "i": "🤲", "c": "poluchenie"}, {"s": "kakie-dannye-nuzhno-dlya-polucheniya-posylki-v-sdek", "t": "Какие данные нужны для получения посылки в СДЭК: полный список 2026", "i": "🤲", "c": "poluchenie"}, {"s": "kakie-dannye-nuzhny-chtob-otpravit-sdek", "t": "Какие данные нужны для отправки посылки через СДЭК в 2026 году", "i": "🚚", "c": "otpravka-gruzov"}, {"s": "kakie-dannye-nuzhny-dlya-togo-chtoby-otpravit-posylku-sdek", "t": "Какие данные нужны для отправки посылки СДЭК в 2026 году", "i": "🚚", "c": "otpravka-gruzov"}, {"s": "kakie-podklyuchenie-sdek", "t": "Как подключиться к СДЭК: все способы для физических и юридических лиц", "i": "🤝", "c": "biznes-i-dogovory"}, {"s": "kakim-transportom-otpravlyayut-posylki-sdek", "t": "Каким транспортом СДЭК доставляет посылки в 2026 году: виды и особенности", "i": "🚚", "c": "otpravka-gruzov"}, {"s": "kakim-transportom-sdek-perevozit-posylki", "t": "Каким транспортом СДЭК доставляет посылки в 2026 году: виды, особенности, сроки", "i": "🚚", "c": "otpravka-gruzov"}, {"s": "kakaya-zarplata-v-sdek-otzyvy-sotrudnikov", "t": "Зарплата в СДЭК 2026: реальные отзывы сотрудников и актуальные данные", "i": "📁", "c": "drugoe"}, {"s": "kakie-gruzy-vyyavlennye-v-lichnykh-veshchakh-fizicheskikh-lits-razresheny-k-perevozke-sdek", "t": "Какие грузы в личных вещах можно отправлять через СДЭК в 2026 году", "i": "🧊", "c": "spetsgruzy"}, {"s": "kakie-integrirovat-sdek", "t": "Какие сервисы интегрировать с СДЭК: полный гайд 2026", "i": "🤝", "c": "biznes-i-dogovory"}, {"s": "kakie-dannye-nado-ukazyvat-pri-otpravke-posylki-cherez-sdek", "t": "Какие данные указывать при отправке посылки через СДЭК в 2026 году", "i": "🚚", "c": "otpravka-gruzov"}, {"s": "kakim-transportom-dostavlyaet-sdek", "t": "Каким транспортом доставляет СДЭК: виды, скорость и особенности", "i": "🚚", "c": "otpravka-gruzov"}, {"s": "kakaya-podklyuchit-sdek", "t": "Как подключить СДЭК: пошаговая инструкция для физических и юридических лиц", "i": "🤝", "c": "biznes-i-dogovory"}, {"s": "kakaya-tk-deshevle-sdek-ili-energiya", "t": "СДЭК или Энергия: где дешевле отправить посылку в 2026 году?", "i": "💳", "c": "oplata-i-tarify"}, {"s": "kakaya-ustanovit-sdek", "t": "Какую СДЭК установить в 2026: сравнение тарифов и условий для физических и юридических лиц", "i": "🤝", "c": "biznes-i-dogovory"}, {"s": "kakie-dokumenty-dlya-polucheniya-posylki-sdek", "t": "Какие документы нужны для получения посылки СДЭК в 2026 году", "i": "🤲", "c": "poluchenie"}, {"s": "kakie-nuzhny-dannye-chtoby-otpravit-posylku-sdekom", "t": "Какие данные нужны для отправки посылки СДЭКом в 2026 году", "i": "🚚", "c": "otpravka-gruzov"}, {"s": "kakoj-nomer-nuzhen-dlya-otslezhivaniya-sdek", "t": "Какой номер нужен для отслеживания посылки СДЭК: полный гайд 2026", "i": "🔍", "c": "otslezhivanie"}, {"s": "kakie-dannye-nuzhny-chtoby-otpravit-sdek", "t": "Какие данные нужны для отправки посылки через СДЭК в 2026 году", "i": "🚚", "c": "otpravka-gruzov"}, {"s": "kakie-marketplejsy-dostavlyayut-v-sdek", "t": "Какие маркетплейсы доставляют товары через СДЭК в 2026 году", "i": "🤲", "c": "poluchenie"}, {"s": "kakie-dannye-nuzhny-chtoby-otpravit-posylku-sdek", "t": "Какие данные нужны для отправки посылки СДЭК в 2026 году", "i": "🚚", "c": "otpravka-gruzov"}, {"s": "kakie-dannye-nuzhny-dlya-otpravki-sdek-do-punkta-vydachi-zakazov", "t": "Какие данные нужны для отправки СДЭК до пункта выдачи заказов в 2026", "i": "🚚", "c": "otpravka-gruzov"}, {"s": "kakie-dokumenty-dlya-otpravki-posylki-sdek", "t": "Документы для отправки посылки СДЭК в 2026: полный список и правила", "i": "🚚", "c": "otpravka-gruzov"}, {"s": "kakie-dokumenty-nuzhny-pri-otpravke-sdek", "t": "Документы для отправки посылки СДЭК в 2026 году — полный список", "i": "🚚", "c": "otpravka-gruzov"}, {"s": "kakie-produkty-mozhno-otpravit-sdek", "t": "Какие продукты можно отправить через СДЭК: список и правила 2026", "i": "🧊", "c": "spetsgruzy"}, {"s": "kakim-transportom-dostavlyayutsya-posylki-sdek-po-rossii-v-punkt-vydachi", "t": "Как СДЭК доставляет посылки по России в пункты выдачи: виды транспорта", "i": "🔍", "c": "otslezhivanie"}, {"s": "kakoj-indeks-ukazyvat-pri-zakaze-posylki-sdek", "t": "Какой индекс указывать при заказе посылки в СДЭК: инструкция 2026", "i": "🚚", "c": "otpravka-gruzov"}, {"s": "kakaya-tk-luchshe-sdek-ili-energiya", "t": "СДЭК или Энергия: какая транспортная компания лучше в 2026 году?", "i": "🤲", "c": "poluchenie"}, {"s": "kakie-est-upakovki-v-sdek", "t": "Упаковки СДЭК: виды, требования и советы по выбору в 2026 году", "i": "🚚", "c": "otpravka-gruzov"}, {"s": "kakie-posylki-mozhno-otpravlyat-sdekom", "t": "Что можно отправлять через СДЭК: правила и ограничения 2026", "i": "🚚", "c": "otpravka-gruzov"}, {"s": "kakaya-forma-sobstvennosti-kompanii-sdek", "t": "СДЭК: форма собственности компании в 2026 году — ОАО, АО или ИП?", "i": "🤝", "c": "biznes-i-dogovory"}, {"s": "kakaya-informatsiya-nuzhna-chtoby-otpravit-posylku-sdek", "t": "Какая информация нужна для отправки посылки через СДЭК в 2026 году", "i": "🚚", "c": "otpravka-gruzov"}, {"s": "kakie-dannye-nuzhno-dlya-otpravki-sdek-dlya-poluchatelya", "t": "Какие данные нужны для отправки СДЭК получателю: полный список 2026", "i": "🚚", "c": "otpravka-gruzov"}, {"s": "kakie-strany-obsluzhivaet-sdek", "t": "СДЭК: в какие страны доставляет посылки в 2026 году? Полный список", "i": "🚚", "c": "otpravka-gruzov"}, {"s": "kakoj-protsent-platit-sdeka", "t": "Какой процент берёт СДЭК за доставку: тарифы 2026 и скрытые комиссии", "i": "💳", "c": "oplata-i-tarify"}, {"s": "kakoj-tip-zakaza-pozvolyaet-rabotat-s-nalozhennym-platezhom-v-sdek", "t": "Наложенный платёж в СДЭК: какой тип заказа выбрать в 2026 году", "i": "💳", "c": "oplata-i-tarify"}, {"s": "kaluzhskoe-shosse-1a-sdek-kak-najti", "t": "СДЭК на Калужском шоссе, 1А: как найти пункт выдачи и не заблудиться", "i": "📍", "c": "punkty-i-adresa"}, {"s": "kakaya-zarplata-u-kurera-sdek", "t": "Зарплата курьера СДЭК в 2026: реальные цифры и условия работы", "i": "💳", "c": "oplata-i-tarify"}, {"s": "kakie-dannye-nuzhny-dlya-posylki-sdek-poluchatelya", "t": "Какие данные нужны для посылки СДЭК получателю в 2026 году", "i": "🚚", "c": "otpravka-gruzov"}, {"s": "kakie-usloviya-dlya-otpravki-yuvelirnykh-izdelij-yavlyayutsya-obyazatelnymi-sdek", "t": "Условия отправки ювелирных изделий через СДЭК в 2026 году", "i": "🧊", "c": "spetsgruzy"}, {"s": "kakim-obrazom-opredelyaetsya-vozmozhnost-prinyatiya-gruza-k-perevozke-opredelyaetsya-kharakter-gruza-sdek", "t": "Как СДЭК определяет возможность перевозки груза: критерии и правила 2026", "i": "🧊", "c": "spetsgruzy"}, {"s": "kakie-dokumenty-neobkhodimy-dlya-otpravki-posylki-sdek", "t": "Документы для отправки посылки СДЭК в 2026: полный список и нюансы", "i": "🚚", "c": "otpravka-gruzov"}, {"s": "kakie-dokumenty-nuzhny-chtoby-otpravit-posylku-cherez-sdek", "t": "Какие документы нужны для отправки посылки через СДЭК в 2026 году", "i": "🚚", "c": "otpravka-gruzov"}, {"s": "kakie-dokumenty-nuzhny-dlya-posylki-sdek", "t": "Документы для посылки СДЭК 2026: полный список и правила оформления", "i": "🚚", "c": "otpravka-gruzov"}, {"s": "kakoj-srok-khraneniya-posylki-v-sdek", "t": "Срок хранения посылок в СДЭК 2026: сколько дней можно не забирать?", "i": "🤲", "c": "poluchenie"}, {"s": "kakie-dannye-dlya-otpravki-sdekom", "t": "Какие данные нужны для отправки посылки через СДЭК в 2026 году", "i": "🚚", "c": "otpravka-gruzov"}, {"s": "kakie-dannye-nuzhny-chtoby-otpravit-posylku-sdek-v-drugoj-gorod", "t": "Какие данные нужны для отправки посылки СДЭК в другой город", "i": "🚚", "c": "otpravka-gruzov"}, {"s": "kakie-dannye-nuzhny-dlya-dostavki-sdek", "t": "Какие данные нужны для доставки СДЭК в 2026 году: полный чек-лист", "i": "🚚", "c": "otpravka-gruzov"}, {"s": "kakie-dannye-nuzhny-dlya-otpravki-sdek-do-punkta", "t": "Какие данные нужны для отправки СДЭК до пункта выдачи — полный список 2026", "i": "🚚", "c": "otpravka-gruzov"}, {"s": "kakoj-dolzhen-byt-login-dlya-registratsii-v-sdek", "t": "Какой логин выбрать для регистрации в СДЭК: правила и советы 2026", "i": "🆔", "c": "sdek-id"}, {"s": "kakuyu-pribyl-prinosit-sdeka", "t": "Сколько зарабатывает СДЭК: прибыль, доходы и финансовые показатели 2026", "i": "💳", "c": "oplata-i-tarify"}, {"s": "kakaya-integratsiya-sdek", "t": "Интеграция с СДЭК: все способы и нюансы для бизнеса в 2026", "i": "🤝", "c": "biznes-i-dogovory"}, {"s": "kakie-produkty-mozhno-otpravlyat-cherez-sdek", "t": "Какие продукты можно отправлять через СДЭК: правила и ограничения 2026", "i": "🧊", "c": "spetsgruzy"}, {"s": "kakim-vidom-transporta-dostavlyaet-sdek", "t": "Каким транспортом доставляет СДЭК: виды, скорость и нюансы 2026", "i": "🚚", "c": "otpravka-gruzov"}, {"s": "kakaya-upakovka-v-sdek", "t": "Какая упаковка нужна для отправки в СДЭК: требования 2026 и советы по выбору", "i": "🚚", "c": "otpravka-gruzov"}, {"s": "kakie-dannye-nuzhny-dlya-otpravki-sdek-nalozhennym-platezhom", "t": "Какие данные нужны для отправки СДЭК наложенным платежом: полный список 2026", "i": "💳", "c": "oplata-i-tarify"}, {"s": "kakie-dannye-nuzhny-dlya-peresylki-sdekom", "t": "Какие данные нужны для пересылки посылки СДЭК: полный список 2026", "i": "🚚", "c": "otpravka-gruzov"}, {"s": "kakie-dannye-poluchatelya-trebuet-sdek", "t": "Какие данные получателя требует СДЭК в 2026 году: полный список", "i": "🤲", "c": "poluchenie"}, {"s": "kakoj-maksimalnyj-ves-posylki-mozhno-otpravit-cherez-sdek", "t": "Максимальный вес посылки СДЭК в 2026: тарифы и ограничения", "i": "🚚", "c": "otpravka-gruzov"}, {"s": "kakie-dannye-nuzhny-chtoby-otpravit-posylku-sdekom", "t": "Какие данные нужны для отправки посылки СДЭК: полный список 2026", "i": "🚚", "c": "otpravka-gruzov"}, {"s": "kakie-dannye-trebuyutsya-dlya-otpravki-sdek", "t": "Какие данные нужны для отправки посылки через СДЭК в 2026 году", "i": "🚚", "c": "otpravka-gruzov"}, {"s": "kakie-nuzhny-dokumenty-dlya-polucheniya-posylki-v-sdek", "t": "Какие документы нужны для получения посылки в СДЭК в 2026 году", "i": "🤲", "c": "poluchenie"}, {"s": "kakim-transportom-dostavlyaet-sdek-posylki", "t": "Как СДЭК доставляет посылки: виды транспорта и маршруты 2026", "i": "🚚", "c": "otpravka-gruzov"}, {"s": "kakaya-informatsiya-nuzhna-dlya-polucheniya-posylki-sdek", "t": "Какие данные нужны для получения посылки СДЭК в 2026 году", "i": "🤲", "c": "poluchenie"}, {"s": "kakaya-informatsiya-nuzhna-dlya-polucheniya-sdek", "t": "Какие документы нужны для получения посылки в СДЭК: полный список 2026", "i": "🤲", "c": "poluchenie"}, {"s": "kakaya-komissiya-u-sdek-pri-nalozhennom-platezhe", "t": "Комиссия СДЭК при наложенном платеже в 2026 году: тарифы и нюансы", "i": "💳", "c": "oplata-i-tarify"}, {"s": "kakaya-tk-deshevle-pek-ili-sdek", "t": "ПЭК или СДЭК — какая ТК дешевле в 2026? Сравнение тарифов", "i": "💳", "c": "oplata-i-tarify"}, {"s": "kakie-dannye-nuzhny-chtob-otpravit-posylku-sdekom", "t": "Какие данные нужны для отправки посылки через СДЭК в 2026 году", "i": "🚚", "c": "otpravka-gruzov"}, {"s": "kakie-dannye-nuzhny-dlya-posylki-sdek", "t": "Какие данные нужны для посылки СДЭК в 2026: полный чек-лист", "i": "🚚", "c": "otpravka-gruzov"}, {"s": "kakie-dokumenty-nuzhny-dlya-otpravki-sdekom", "t": "Какие документы нужны для отправки посылки СДЭК в 2026 году", "i": "🚚", "c": "otpravka-gruzov"}, {"s": "kakie-produkty-mozhno-otpravlyat-sdekom", "t": "Какие товары можно отправлять через СДЭК: полный список 2026", "i": "🧊", "c": "spetsgruzy"}, {"s": "kakaya-oplata-v-sdek", "t": "Оплата за доставку СДЭК в 2026: тарифы, способы и нюансы", "i": "💳", "c": "oplata-i-tarify"}, {"s": "kakaya-pribyl-ot-punkta-vydachi-sdek", "t": "Прибыль пункта выдачи СДЭК: расчет доходов и затрат в 2026 году", "i": "📍", "c": "punkty-i-adresa"}, {"s": "kakie-dannye-nuzhny-dlya-otpravki-posylki-sdek-za-schet-poluchatelya", "t": "Какие данные нужны для отправки посылки СДЭК за счёт получателя в 2026 году", "i": "🚚", "c": "otpravka-gruzov"}, {"s": "kakie-dokumenty-nuzhny-chtoby-otpravit-sdekom", "t": "Какие документы нужны для отправки посылки СДЭК в 2026 году", "i": "🚚", "c": "otpravka-gruzov"}, {"s": "kakie-posylki-dostavlyaet-sdek", "t": "Что доставляет СДЭК: виды посылок и ограничения 2026 года", "i": "🚚", "c": "otpravka-gruzov"}, {"s": "kakim-transportom-otpravlyaet-sdek", "t": "Каким транспортом СДЭК доставляет посылки в 2026 году: виды, сроки, особенности", "i": "🚚", "c": "otpravka-gruzov"}, {"s": "kakoj-adres-ukazyvat-dlya-polucheniya-posylki-sdek", "t": "Какой адрес указать для получения посылки СДЭК в 2026 году", "i": "📍", "c": "punkty-i-adresa"}, {"s": "kakoj-nomer-sdek", "t": "Какой номер СДЭК у посылки? Где найти и как использовать", "i": "🔍", "c": "otslezhivanie"}, {"s": "kakie-dannye-nuzhny-dlya-otpravleniya-posylki-sdekom", "t": "Какие данные нужны для отправки посылки СДЭК: полный список 2026", "i": "🚚", "c": "otpravka-gruzov"}, {"s": "kakoj-nalozhennyj-platezh-v-sdeke", "t": "Наложенный платеж в СДЭК 2026: правила, комиссии и ограничения", "i": "💳", "c": "oplata-i-tarify"}, {"s": "kakie-dannye-nuzhny-pri-otpravke-posylki-sdek", "t": "Какие данные нужны для отправки посылки СДЭК в 2026 году: полный чек-лист", "i": "🚚", "c": "otpravka-gruzov"}, {"s": "kakie-dokumenty-nuzhny-chtob-otpravit-posylku-cherez-sdek", "t": "Документы для отправки посылки через СДЭК в 2026 году: полный список", "i": "🚚", "c": "otpravka-gruzov"}, {"s": "kakie-otpravleniya-zapreshcheny-k-perevozke-v-nashej-transportnoj-kompanii-sdek", "t": "Что нельзя отправлять через СДЭК: полный список запрещённых грузов 2026", "i": "🧊", "c": "spetsgruzy"}, {"s": "kakoj-gruz-schitaetsya-tyazhelym-sdek", "t": "Тяжелый груз в СДЭК: весовые нормы, тарифы и правила перевозки 2026", "i": "🧊", "c": "spetsgruzy"}, {"s": "kakaya-nastrojka-sdek", "t": "Какая настройка СДЭК: выбор доставки и опций", "i": "🚚", "c": "otpravka-gruzov"}, {"s": "kakie-instrumenty-pozitivno-vliyayushchie-na-sobesednika-ty-teper-znaesh-sdek", "t": "Инструменты влияния на собеседника в СДЭК: психология общения", "i": "🤝", "c": "biznes-i-dogovory"}, {"s": "kakaya-dobavit-sdek", "t": "Как добавить СДЭК: инструкции для отправителей и получателей", "i": "📁", "c": "drugoe"}, {"s": "kakie-nuzhny-dokumenty-chtoby-poluchit-posylku-v-sdek", "t": "Документы для получения посылки в СДЭК: полный список 2026", "i": "🤲", "c": "poluchenie"}, {"s": "kakaya-pribyl-ot-punkta-vydachi-sdeka", "t": "Прибыль пункта выдачи СДЭК: расчеты и расходы 2026-2026", "i": "📍", "c": "punkty-i-adresa"}, {"s": "kakie-dokumenty-nuzhny-pri-otpravke-gruza-sdek", "t": "Какие документы нужны для отправки груза СДЭК: полный список", "i": "🚚", "c": "otpravka-gruzov"}, {"s": "kakie-neobkhodimy-dannye-dlya-otpravki-sdek", "t": "Какие данные нужны для отправки СДЭК: полный список полей", "i": "🚚", "c": "otpravka-gruzov"}, {"s": "kakie-dannye-nuzhny-chtoby-otpravit-sdekom", "t": "Какие данные нужны для СДЭК: полный список документов", "i": "🚚", "c": "otpravka-gruzov"}, {"s": "kakie-podklyuchit-sdek", "t": "Какие подключить СДЭК: тарифы и договоры для бизнеса", "i": "🤝", "c": "biznes-i-dogovory"}, {"s": "kakie-korobki-v-sdek-est", "t": "Какие коробки есть в СДЭК: размеры, цены и виды упаковки", "i": "🚚", "c": "otpravka-gruzov"}, {"s": "kakie-korobki-v-sdek", "t": "Какие коробки в СДЭК: размеры, цены и типы упаковки", "i": "🚚", "c": "otpravka-gruzov"}, {"s": "kakoj-srok-khraneniya-v-sdeke", "t": "Срок хранения в СДЭК: тарифы, продление и штрафы", "i": "🤲", "c": "poluchenie"}, {"s": "kakie-instrumenty-pozitivno-vliyayushchie-na-sobesednika-ty-teper-znaesh-sdek-otvety", "t": "Какие инструменты позитивно влияют на собеседника в СДЭК: ответы", "i": "⚠️", "c": "problemy-i-vozvrat"}, {"s": "kakie-dannye-poluchatelya-nuzhny-v-sdeke", "t": "Какие данные получателя нужны в СДЭК: полный список", "i": "🤲", "c": "poluchenie"}, {"s": "kakaya-nastroit-sdek", "t": "Как настроить СДЭК: полная инструкция для отправителей", "i": "🤝", "c": "biznes-i-dogovory"}, {"s": "kakie-dobavit-sdek", "t": "Какие добавить СДЭК: настройка виджетов, опций и способов оплаты", "i": "🤝", "c": "biznes-i-dogovory"}, {"s": "kakie-dokumenty-nuzhny-dlya-polucheniya-gruza-transportnoj-kompaniej-sdek", "t": "Какие документы нужны для получения груза СДЭК: полный список", "i": "🤲", "c": "poluchenie"}, {"s": "kakoj-sdek-prinimaet-krupnyj-gruz", "t": "Какой СДЭК принимает крупный груз: лимиты и правила", "i": "🧊", "c": "spetsgruzy"}, {"s": "kakie-gruzy-perevozit-sdek", "t": "Какие грузы перевозит СДЭК: полный список и ограничения", "i": "🧊", "c": "spetsgruzy"}, {"s": "kakie-korobki-est-v-sdek-razmery", "t": "Какие коробки есть в СДЭК: размеры и цены 2026", "i": "📁", "c": null}, {"s": "kakoj-mss-kod-u-sdek", "t": "Какой МСС код у СДЭК: таблица для банковских выписок", "i": "💳", "c": "oplata-i-tarify"}, {"s": "kakie-dannye-nuzhny-dlya-sdek-dlya-polucheniya", "t": "Какие данные нужны для СДЭК для получения: полный список документов", "i": "📁", "c": null}, {"s": "kakie-dannye-nuzhny-sdek-dlya-otpravki-chastnomu-litsu", "t": "Какие данные нужны СДЭК для отправки частному лицу: полный список", "i": "🚚", "c": "otpravka-gruzov"}, {"s": "kakie-dokumenty-nuzhny-pri-otpravke-posylki-v-sdek", "t": "Какие документы нужны при отправке посылки в СДЭК", "i": "📁", "c": null}, {"s": "kakie-dannye-nuzhny-chtoby-poluchit-posylku-v-sdek", "t": "Какие данные нужны для получения посылки СДЭК", "i": "🤲", "c": "poluchenie"}, {"s": "kakoj-adres-nuzhen-dlya-sdek", "t": "Какой адрес нужен для СДЭК: форматы и правила ввода", "i": "📍", "c": "punkty-i-adresa"}, {"s": "kakoj-maksimalnyj-ves-posylki-mozhno-otpravit-sdekom", "t": "Максимальный вес посылки СДЭК: лимиты и тарифы", "i": "🚚", "c": "otpravka-gruzov"}, {"s": "kakie-dannye-nuzhny-dlya-otpravki-sdek-do-punkta-vydachi", "t": "Какие данные нужны для отправки СДЭК до пункта выдачи", "i": "📁", "c": null}, {"s": "kakie-integratsiya-sdek", "t": "Интеграции СДЭК: API, модули CMS и сервисы для бизнеса", "i": "🤝", "c": "biznes-i-dogovory"}, {"s": "kakie-posylki-mozhno-otpravit-sdek", "t": "Что можно отправить СДЭК: полный список разрешенных грузов", "i": "🚚", "c": "otpravka-gruzov"}, {"s": "kakie-gruzy-otnosyatsya-k-oruzhiyu-sdek", "t": "Какие грузы относятся к оружию СДЭК: правила 2026", "i": "🧊", "c": "spetsgruzy"}, {"s": "kakim-transportom-dostavlyayutsya-posylki-sdek-po-rossii", "t": "Транспорт СДЭК: как доставляют посылки по России", "i": "🚚", "c": "otpravka-gruzov"}, {"s": "kakie-dannye-nuzhny-dlya-otpravki-sdek-fiz-litsu", "t": "Какие данные нужны для отправки СДЭК физ лицу: полный список", "i": "🚚", "c": "otpravka-gruzov"}, {"s": "kakoj-protsent-sdek-za-nalozhennyj-platezh-beret", "t": "Комиссия СДЭК за наложенный платеж: тарифы 2026", "i": "💳", "c": "oplata-i-tarify"}, {"s": "kakuyu-informatsiyu-operator-mozhet-izmenit-so-slov-otpravitelya-bez-identifikatsii-sdek", "t": "Изменение данных отправителя СДЭК без ID: риски и правила", "i": "🛡️", "c": "bezopasnost"}, {"s": "kakie-dannye-nuzhny-dlya-otpravki-gruza-v-sdek", "t": "Документы для СДЭК: что нужно для отправки груза", "i": "🚚", "c": "otpravka-gruzov"}, {"s": "kakoj-srok-khraneniya-posylok-v-sdek", "t": "Срок хранения посылок в СДЭК: правила и условия 2026", "i": "🤲", "c": "poluchenie"}, {"s": "kakie-dannye-nuzhny-dlya-otpravki-posylki-sdek-transportnoj-kompaniej", "t": "Какие данные нужны для отправки посылки СДЭК: полный список", "i": "🚚", "c": "otpravka-gruzov"}, {"s": "kakie-dokumenty-nuzhny-pri-otpravke-posylki-sdekom", "t": "Документы для отправки СДЭК: полный список и требования", "i": "🚚", "c": "otpravka-gruzov"}, {"s": "kakie-nuzhny-dannye-dlya-otpravki-posylki-sdekom", "t": "Какие данные нужны для отправки посылки СДЭКом: полный список", "i": "🚚", "c": "otpravka-gruzov"}, {"s": "kakoj-srok-besplatnogo-khraneniya-v-sdek", "t": "Срок бесплатного хранения в СДЭК: тарифы, условия, продление", "i": "📁", "c": null}, {"s": "kakaya-nuzhna-informatsiya-dlya-otpravki-posylki-sdek", "t": "Какая информация нужна для отправки посылки СДЭК", "i": "🚚", "c": "otpravka-gruzov"}, {"s": "kakie-ustanovit-sdek", "t": "Какие установить СДЭК: выбор модуля для сайта и приложения", "i": "🤝", "c": "biznes-i-dogovory"}, {"s": "kakie-dannye-neobkhodimy-dlya-polucheniya-posylki-v-sdek", "t": "Какие данные нужны для получения посылки СДЭК: полный список документов", "i": "🤲", "c": "poluchenie"}, {"s": "kakie-dannye-nuzhny-dlya-dostavki-sdekom", "t": "Какие данные нужны для доставки СДЭК: полный список реквизитов", "i": "🚚", "c": "otpravka-gruzov"}, {"s": "kakie-dobavlenie-sdek", "t": "Какие добавления СДЭК: полное руководство по опциям и услугам", "i": "💳", "c": "oplata-i-tarify"}, {"s": "kakie-nuzhny-dokumenty-pri-poluchenii-posylki-sdek", "t": "Какие документы нужны для получения посылки СДЭК: полный список", "i": "🤲", "c": "poluchenie"}, {"s": "kakie-dannye-nuzhny-chtoby-otpravit-posylku-sdekom-cheloveku", "t": "Какие данные нужны для отправки СДЭК: полный список", "i": "🚚", "c": "otpravka-gruzov"}, {"s": "kakim-transportom-sdek-osushchestvlyaet-dostavku", "t": "Каким транспортом СДЭК доставляет грузы: авто, авиа и ж/д", "i": "🧊", "c": "spetsgruzy"}, {"s": "kakoj-kod-nuzhno-vvodit-v-sdek", "t": "Какой код вводить в СДЭК: инструкции по трекам и паролям", "i": "🤲", "c": "poluchenie"}, {"s": "kakie-dokumenty-nuzhny-dlya-sdek", "t": "Какие документы нужны для СДЭК: полный список 2026", "i": "🚚", "c": "otpravka-gruzov"}, {"s": "kakie-tsennosti-u-kompanii-sdek", "t": "Ценности компании СДЭК: миссия, принципы и стандарты", "i": "🤝", "c": "biznes-i-dogovory"}, {"s": "kakie-uslugi-predostavlyaet-sdek", "t": "Какие услуги предоставляет СДЭК: полный список и описание", "i": "📁", "c": "drugoe"}, {"s": "kakie-dannye-nuzhny-dlya-oformleniya-sdek", "t": "Какие данные нужны для оформления СДЭК: полный список", "i": "🚚", "c": "otpravka-gruzov"}, {"s": "kakie-dannye-nuzhny-dlya-sdek-dlya-poluchatelya", "t": "Какие данные нужны для СДЭК получателю: полный список", "i": "🤲", "c": "poluchenie"}, {"s": "kakoj-transport-ispolzuyut-v-sdek", "t": "Какой транспорт использует СДЭК: автопарк и логистика", "i": "🧊", "c": "spetsgruzy"}, {"s": "kakie-dannye-dlya-dostavki-sdek", "t": "Какие данные нужны для доставки СДЭК: полный список реквизитов", "i": "🚚", "c": "otpravka-gruzov"}, {"s": "kakie-formaty-dogovornoj-raboty-dostupny-v-sdek", "t": "Форматы договорной работы СДЭК: виды, условия и подключение", "i": "🤝", "c": "biznes-i-dogovory"}, {"s": "kakie-dannye-nuzhny-dlya-otpravki-posylki-sdek", "t": "Какие данные нужны для отправки посылки СДЭК: полный список", "i": "🚚", "c": "otpravka-gruzov"}, {"s": "kakie-nastroit-sdek", "t": "Как настроить СДЭК: личный кабинет, уведомления и интеграции", "i": "🤝", "c": "biznes-i-dogovory"}, {"s": "kakie-dokumenty-dlya-otpravki-sdek", "t": "Документы для отправки СДЭК: полный список 2026-2026", "i": "🚚", "c": "otpravka-gruzov"}, {"s": "kakie-dannye-nuzhny-dlya-otpravki-posylki-pochtoj-sdek", "t": "Какие данные нужны для отправки СДЭК: полный список", "i": "🚚", "c": "otpravka-gruzov"}, {"s": "kakie-nado-dannye-dlya-otpravki-sdek", "t": "Какие данные нужны для отправки СДЭК: полный список документов", "i": "🚚", "c": "otpravka-gruzov"}, {"s": "kakie-dannye-nuzhny-dlya-otpravki-transportnoj-kompanii-sdek", "t": "Какие данные нужны для отправки СДЭК: полный список реквизитов", "i": "🚚", "c": "otpravka-gruzov"}, {"s": "kakie-posylki-otpravlyaet-sdek", "t": "Какие посылки отправляет СДЭК: полный список грузов", "i": "📁", "c": null}, {"s": "kakie-instrumenty-pozitivno-vliyayushchie-na-sobesednika-sdek", "t": "Инструменты СДЭК, позитивно влияющие на клиента: как улучшить опыт", "i": "🤝", "c": "biznes-i-dogovory"}, {"s": "kakim-transportom-dostavlyayut-posylki-sdek", "t": "Транспорт СДЭК: каким видом доставляют посылки?", "i": "🚚", "c": "otpravka-gruzov"}, {"s": "kakie-dannye-nuzhny-dlya-otpravki-posylki-sdek-nalozhennym-platezhom", "t": "Какие данные нужны для отправки посылки СДЭК наложенным платежом", "i": "💳", "c": "oplata-i-tarify"}, {"s": "kakoj-dokument-nuzhen-dlya-polucheniya-posylki-v-sdek", "t": "Документы для получения посылок в СДЭК: полный список 2026", "i": "🤲", "c": "poluchenie"}, {"s": "kakaya-pribyl-ot-sdeka", "t": "Прибыль от СДЭК: сколько можно заработать на франшизе", "i": "🤝", "c": "biznes-i-dogovory"}, {"s": "kakaya-zarplata-v-sdek", "t": "Зарплата в СДЭК 2026: обзор окладов и бонусов", "i": "💳", "c": "oplata-i-tarify"}, {"s": "kakie-dannye-nuzhny-dlya-otpravki-posylki-v-sdeke", "t": "Какие данные нужны для отправки посылки в СДЭК: полный список", "i": "🚚", "c": "otpravka-gruzov"}, {"s": "kakie-dannye-poluchatelya-nuzhny-dlya-otpravki-sdekom", "t": "Какие данные получателя нужны для отправки СДЭК: полный список", "i": "🚚", "c": "otpravka-gruzov"}, {"s": "kakoj-dokhod-ot-franshizy-sdek", "t": "Доход от франшизы СДЭК: расчеты, цифры и реальная прибыль", "i": "🤝", "c": "biznes-i-dogovory"}, {"s": "kakaya-integrirovat-sdek", "t": "Какую карту интегрировать с СДЭК: полное руководство", "i": "📁", "c": null}, {"s": "kakie-dannye-neobkhodimy-dlya-otpravki-posylki-sdek", "t": "Какие данные нужны для отправки посылки СДЭК: полный список", "i": "🚚", "c": "otpravka-gruzov"}, {"s": "kakie-dannye-poluchatelya-neobkhodimy-pri-otpravke-sdek", "t": "Какие данные получателя нужны для СДЭК: полный список", "i": "🚚", "c": "otpravka-gruzov"}, {"s": "kakie-rekvizity-nuzhny-dlya-otpravki-sdek", "t": "Какие реквизиты нужны для отправки СДЭК: полный список", "i": "🚚", "c": "otpravka-gruzov"}, {"s": "kakie-skrytye-opasnye-i-zapreshchennye-gruzy-mozhet-soderzhat-vodolaznoe-oborudovanie-sdek", "t": "Опасные грузы в водолазном снаряжении СДЭК: что нельзя отправлять", "i": "🧊", "c": "spetsgruzy"}, {"s": "kakie-dannye-nuzhny-dlya-otpravki-transportnoj-kompaniej-sdek", "t": "Какие данные нужны для отправки СДЭК: полный список документов", "i": "🚚", "c": "otpravka-gruzov"}, {"s": "kakie-dokumenty-vydaet-sdek-pri-otpravke-posylki", "t": "Документы СДЭК при отправке: чеки, накладные, описи", "i": "🚚", "c": "otpravka-gruzov"}, {"s": "kakaya-tk-deshevle-sdek-ili-kit", "t": "Что дешевле: СДЭК или КИТ? Сравнение тарифов 2026", "i": "💳", "c": "oplata-i-tarify"}, {"s": "kakie-dokumenty-nuzhny-pri-otpravke-sdekom", "t": "Какие документы нужны для отправки СДЭК: полный список 2026", "i": "🚚", "c": "otpravka-gruzov"}, {"s": "kakaya-transportnaya-kompaniya-sdek", "t": "Какая транспортная компания СДЭК: обзор, услуги и возможности", "i": "📁", "c": "drugoe"}, {"s": "kakoj-dolzhen-byt-trek-nomer-sdek", "t": "Какой должен быть трек-номер СДЭК: форматы и проверка", "i": "🔍", "c": "otslezhivanie"}, {"s": "kakie-dannye-nuzhny-chtob-otpravit-sdekom", "t": "Какие данные нужны, чтобы отправить СДЭК: полный список документов", "i": "📁", "c": null}, {"s": "kakie-dannye-nuzhny-dlya-otpravki-tk-sdek", "t": "Какие данные нужны для отправки ТК СДЭК: полный список", "i": "🚚", "c": "otpravka-gruzov"}, {"s": "kakie-sroki-dostavki-sdek", "t": "Сроки доставки СДЭК: актуальные нормативы 2026-2026 гг.", "i": "🔍", "c": "otslezhivanie"}, {"s": "kakie-dannye-neobkhodimy-chtoby-otpravit-posylku-cherez-sdek", "t": "Какие данные нужны для отправки посылки СДЭК: полный список документов", "i": "🚚", "c": "otpravka-gruzov"}, {"s": "kakoj-kod-vvodit-v-postamate-sdek", "t": "Какой код вводить в постамате СДЭК: инструкция", "i": "🤲", "c": "poluchenie"}, {"s": "kakie-dannye-poluchatelya-neobkhodimy-dlya-otpravki-sdek", "t": "Какие данные получателя нужны для СДЭК: полный список", "i": "🚚", "c": "otpravka-gruzov"}, {"s": "kakie-dannye-nado-chtoby-otpravit-posylku-v-sdek", "t": "Какие данные нужны, чтобы отправить посылку в СДЭК: полный список", "i": "🚚", "c": "otpravka-gruzov"}, {"s": "kakie-dannye-nuzhny-pri-otpravke-sdekom", "t": "Какие данные нужны для отправки СДЭК: полный список документов", "i": "🚚", "c": "otpravka-gruzov"}, {"s": "kakie-dokumenty-nuzhny-chtoby-otpravit-sdek", "t": "Документы для СДЭК: список для отправлений 2026", "i": "🚚", "c": "otpravka-gruzov"}, {"s": "kakie-dokumenty-nuzhny-dlya-polucheniya-tovara-v-sdek", "t": "Документы для получения товара в СДЭК: полный список 2026", "i": "🤲", "c": "poluchenie"}, {"s": "kakie-dannye-nuzhny-dlya-otpravki-sdek-poluchatelyu", "t": "Какие данные нужны для отправки СДЭК: полный список 2026", "i": "🚚", "c": "otpravka-gruzov"}, {"s": "kakie-dannye-nuzhny-dlya-sdek-nalozhennym-platezhom", "t": "Какие данные нужны для СДЭК наложенным платежом", "i": "💳", "c": "oplata-i-tarify"}, {"s": "kakoj-maksimalnyj-ves-posylki-sdek", "t": "Максимальный вес посылки СДЭК: лимиты, тарифы и правила", "i": "📁", "c": null}, {"s": "karton-filler-sdek-chto", "t": "Картон-филлер СДЭК: что это, виды и как упаковать", "i": "🚚", "c": "otpravka-gruzov"}, {"s": "kakie-nastrojka-sdek", "t": "Настройка СДЭК: личный кабинет, виджет и API", "i": "🤝", "c": "biznes-i-dogovory"}, {"s": "kakie-dokumenty-nuzhny-dlya-otpravki-posylki-sdek-po-rossii-v-punkt-vydachi", "t": "Документы для отправки СДЭК: полный список 2026", "i": "🚚", "c": "otpravka-gruzov"}, {"s": "kakie-dokumenty-nuzhny-na-otpravku-sdek", "t": "Документы для отправки СДЭК: полный список и правила", "i": "🚚", "c": "otpravka-gruzov"}, {"s": "kakie-est-dostavki-krome-sdek", "t": "Альтернативы СДЭК: Топ-10 служб доставки по России", "i": "🚚", "c": "otpravka-gruzov"}, {"s": "kakaya-luchshe-franshiza-ozon-ili-sdek", "t": "Франшиза Ozon или СДЭК: что выбрать в 2026 году", "i": "🤝", "c": "biznes-i-dogovory"}, {"s": "kakie-razmery-korobok-dlya-posylok-v-sdek", "t": "Размеры коробок для посылок СДЭК: таблица и цены 2026", "i": "🚚", "c": "otpravka-gruzov"}]